pylsb/bible.py
pylsb/data.py
pylsb/parse.py
pylsb/utils.py
pylsb-1.1.0.dist-info/LICENSE
pylsb-1.1.0.dist-info/METADATA
pylsb-1.1.0.dist-info/WHEEL
pylsb-1.1.0.dist-info/top_level.txt
pylsb-1.1.0.dist-info/RECORD
