Metadata-Version: 2.1
Name: pylsb
Version: 1.1.0
Summary: Library for downloading, storing, and retrieving the Legacy Standard Bible.
Author-email: Matthew Rease <scubaventure101@hotmail.com>
License: GNU General Public License v3 (GPLv3)
Project-URL: Homepage, https://gitlab.com/Magicrafter13/pylsb
Project-URL: Issues, https://gitlab.com/Magicrafter13/pylsb/-/issues
Keywords: bible,lsb
Classifier: Development Status :: 5 - Production/Stable
Classifier: Intended Audience :: Developers
Classifier: License :: OSI Approved :: GNU General Public License v3 (GPLv3)
Classifier: Operating System :: OS Independent
Classifier: Programming Language :: Python :: 3
Classifier: Programming Language :: Python :: 3.9
Classifier: Programming Language :: Python :: 3.10
Classifier: Programming Language :: Python :: 3.11
Classifier: Programming Language :: Python :: 3.12
Classifier: Programming Language :: Python :: 3.13
Classifier: Topic :: Religion
Requires-Python: >=3.9
License-File: LICENSE
Requires-Dist: requests
Requires-Dist: beautifulsoup4
Requires-Dist: lxml
